[
  {
    "source": {
      "id": null,
      "name": "Macdailynews.com"
    },
    "author": "MacDailyNews",
    "title": "AAPL investors have opportunity to lead Apple securities fraud lawsuit",
    "description": "AAPL investors now have the opportunity to take a leading role in a securities fraud lawsuit against Apple, as the company faces allegations\u2026\nThe post AAPL investors have opportunity to lead Apple securities fraud lawsuit appeared first on MacDailyNews.",
    "url": "https://macdailynews.com/2025/06/24/aapl-investors-have-opportunity-to-lead-apple-securities-fraud-lawsuit/",
    "urlToImage": "https://149359564.v2.pressablecdn.com/wp-content/uploads/2024/12/241211_apple_intelligence.png",
    "publishedAt": "2025-06-24T15:01:18Z",
    "content": "AAPL investors now have the opportunity to take a leading role in a securities fraud lawsuit against Apple, as the company faces allegations of misleading statements regarding its business practices \u2026 [+1722 chars]"
  },
  {
    "source": {
      "id": null,
      "name": "Barchart.com"
    },
    "author": "Amit Singh",
    "title": "Alphabet Is Undervalued. Should You Buy GOOGL Stock Here?",
    "description": "Alphabet stock is currently trading at levels significantly lower than those of other major tech giants such as MSFT, AAPL, and AMZN.",
    "url": "https://www.barchart.com/story/news/33026524/alphabet-is-undervalued-should-you-buy-googl-stock-here",
    "urlToImage": "https://s.yimg.com/ny/api/res/1.2/WNpA6WoJ2ffjeDmmmTsX8Q--/YXBwaWQ9aGlnaGxhbmRlcjt3PTEyMDA7aD04MDA-/https://media.zenfs.com/en/barchart_com_477/92ef183c42026825f0de825fd26975b4",
    "publishedAt": "2025-06-24T15:37:36Z",
    "content": "Alphabet (Google) Image by Markus Mainka via Shutterstock\r\nAlphabet (GOOGL), the parent company of Google, has seen its shares decline in 2025, with the stock down approximately 11.7% since the start\u2026 [+4723 chars]"
  },
  {
    "source": {
      "id": null,
      "name": "Applech2.com"
    },
    "author": "applech2",
    "title": "Apple Silicon Mac\u3067x86\u30a8\u30df\u30e5\u30ec\u30fc\u30b7\u30e7\u30f3\u30e2\u30fc\u30c9\u3092\u5229\u7528\u3057Windows 10 22H2/Server 2019\u4eee\u60f3\u30de\u30b7\u30f3\u306e\u4f5c\u6210\u3068\u5b9f\u884c\u3092\u30b5\u30dd\u30fc\u30c8\u3057\u305f\u300cParallels Desktop for Mac v20.4.0\u300d\u304c\u30ea\u30ea\u30fc\u30b9\u3002",
    "description": "Apple Silicon Mac\u3067x86\u30a8\u30df\u30e5\u30ec\u30fc\u30b7\u30e7\u30f3\u30e2\u30fc\u30c9\u3092\u5229\u7528\u3057Windows 10 22H2/Server 2019\u4eee\u60f3\u30de\u30b7\u30f3\u306e\u4f5c\u6210\u3068\u5b9f\u884c\u3092\u30b5\u30dd\u30fc\u30c8\u3057\u305f\u300cParallels Desktop for Mac v [\u2026]\nThe post Apple Silicon Mac\u3067x86\u30a8\u30df\u30e5\u30ec\u30fc\u30b7\u30e7\u30f3\u30e2\u30fc\u30c9\u3092\u5229\u7528\u3057Windows 10 22H2/Server 2019\u4eee\u60f3\u30de\u30b7\u30f3\u306e\u4f5c\u6210\u3068\u5b9f\u884c\u3092\u30b5\u30dd\u30fc\u30c8\u3057\u305f\u300cParallels Desktop for Mac v20.4.0\u300d\u304c\u30ea\u30ea\u30fc\u30b9\u3002 first appeare\u2026",
    "url": "https://applech2.com/archives/20250625-parallels-desktop-for-mac-v20-4-0-update.html",
    "urlToImage": "https://applech2.com/wp-content/uploads/2025/06/Parallels-Desktop-for-Mac-20-4-0-features-1.webp",
    "publishedAt": "2025-06-24T21:47:53Z",
    "content": "Apple Silicon Macx86Windows 10 22H2/Server 2019Parallels Desktop for Mac v20.4.0\r\nAlludo(Corel)Parallels International GmbH.2025062404MacParallels Desktop 20 for Mac v20.3.0Parallels Desktop 20 for M\u2026 [+1290 chars]"
  },
  {
    "source": {
      "id": null,
      "name": "Applech2.com"
    },
    "author": "applech2",
    "title": "Hagibis\u3001NVMe SSD\u3068USB\u30cf\u30d6\u63a5\u7d9a\u7528\u306eUSB-C\u30dd\u30fc\u30c8\u3092\u5206\u3051\u308b\u3053\u3068\u3067SSD\u3092Mac mini\u306b\u6700\u592740Gbps\u3067\u63a5\u7d9a\u3067\u304d\u308b\u300cHagibis Mac mini M4 Hub with 40Gbps M.2 SSD Enclosure (MC650)\u300d\u3092\u767a\u58f2\u3002",
    "description": "Hagibis\u304cNVMe SSD\u3068USB\u30cf\u30d6\u63a5\u7d9a\u7528\u306eUSB-C\u30dd\u30fc\u30c8\u3092\u5206\u3051\u308b\u3053\u3068\u3067SSD\u3092Mac mini\u306b\u6700\u592740Gbps\u3067\u63a5\u7d9a\u3067\u304d\u308b\u300cHagibis Mac mini M4 Hub with 40Gbps M.2 [\u2026]\nThe post Hagibis\u3001NVMe SSD\u3068USB\u30cf\u30d6\u63a5\u7d9a\u7528\u306eUSB-C\u30dd\u30fc\u30c8\u3092\u5206\u3051\u308b\u3053\u3068\u3067SSD\u3092Mac mini\u306b\u6700\u592740Gbps\u3067\u63a5\u7d9a\u3067\u304d\u308b\u300cHagibis Mac mini M4 Hub with 40Gbps M.2 SSD Enclosure (MC650)\u300d\u3092\u767a\u58f2\u3002 f\u2026",
    "url": "https://applech2.com/archives/20250624-hagibis-mac-mini-m4-hub-with-40gbps-m2-ssd-enclosure-mc650.html",
    "urlToImage": "https://applech2.com/wp-content/uploads/2025/06/Hagibis-Mac-mini-M4-Hub-with-40Gbps-M2-SSD-Enclosure-Hero.webp",
    "publishedAt": "2025-06-24T06:54:58Z",
    "content": "HagibisNVMe SSDUSBUSB-CSSDMac mini40GbpsHagibis Mac mini M4 Hub with 40Gbps M.2 SSD Enclosure (MC650)\r\nHagibis10GbpsNVMe SSDUSB-CMac mini (2024)Hagibis Mac mini M4 Hub with M.2 SSD Enclosure &amp; Du\u2026 [+564 chars]"
  },
  {
    "source": {
      "id": null,
      "name": "Forbes"
    },
    "author": "Michael Foster, Contributor, \n Michael Foster, Contributor\n https://www.forbes.com/sites/michaelfoster/",
    "title": "These 3 Big Dividends Just Got Cut. They\u2019re Safer Than Ever",
    "description": "If you invest for long enough, you may hear a skeptic of high-yield investments, such as 8%+ yielding closed-end funds (CEFs).",
    "url": "https://www.forbes.com/sites/michaelfoster/2025/06/24/these-3-big-dividends-just-got-cut-theyre-safer-than-ever/",
    "urlToImage": "https://imageio.forbes.com/specials-images/imageserve/6408dca14017498a40ef6518/0x0.jpg?format=jpg&height=900&width=1600&fit=bounds",
    "publishedAt": "2025-06-24T16:17:00Z",
    "content": "Hundred Dollar Bill Being Cut With a Scissor\r\ngetty\r\nIf you invest for long enough, you may hear a skeptic of high-yield investmentssuch as 8%+ yielding closed-end funds (CEFs)say something like:\r\nSu\u2026 [+6366 chars]"
  },
  {
    "source": {
      "id": null,
      "name": "Investor's Business Daily"
    },
    "author": "PATRICK SEITZ, Investor's Business Daily",
    "title": "Microsoft Stock Carves Record High On Agentic AI Leadership",
    "description": "Microsoft stock on Tuesday hit its fourth all-time high in as many trading sessions. The software giant is a leader in agentic AI.",
    "url": "https://www.investors.com/news/technology/microsoft-stock-record-high-agentic-ai/",
    "urlToImage": "https://www.investors.com/wp-content/uploads/2025/06/Stock-Microsoft-CEOSatya-50thann-01-comapny.jpg",
    "publishedAt": "2025-06-24T15:23:12Z",
    "content": "Microsoft (MSFT) stock on Tuesday hit its fourth all-time high in as many trading sessions. The software giant is rising on its leadership position in agentic artificial intelligence applications.\r\nI\u2026 [+2511 chars]"
  },
  {
    "source": {
      "id": null,
      "name": "GlobeNewswire"
    },
    "author": "Bernstein Liebhard LLP",
    "title": "APPLE INC. (NASDAQ: AAPL) INVESTOR ALERT Investors With Large Losses in Apple Inc. Should Contact Bernstein Liebhard LLP To Discuss Their Rights",
    "description": "APPLE INC. (NASDAQ: AAPL) INVESTOR ALERT Investors With Large Losses in Apple Inc. Should Contact Bernstein Liebhard LLP To Discuss Their Rights......",
    "url": "https://www.globenewswire.com/news-release/2025/06/24/3104543/0/en/APPLE-INC-NASDAQ-AAPL-INVESTOR-ALERT-Investors-With-Large-Losses-in-Apple-Inc-Should-Contact-Bernstein-Liebhard-LLP-To-Discuss-Their-Rights.html",
    "urlToImage": "https://ml.globenewswire.com/Resource/Download/5d514042-8326-4555-8ad7-f6cc765ecfcd",
    "publishedAt": "2025-06-24T16:15:00Z",
    "content": "NEW YORK, June 24, 2025 (GLOBE NEWSWIRE) -- Bernstein Liebhard LLP announces that a shareholder has filed a securities class action lawsuit on behalf of investors (the Class) who purchased or acquire\u2026 [+1899 chars]"
  },
  {
    "source": {
      "id": null,
      "name": "GlobeNewswire"
    },
    "author": "Bleichmar Fonti & Auld",
    "title": "AAPL CLASS ACTION NOTICE: Apple Inc. has been Sued for Securities Fraud relating to its AI Rollout \u2013 Investors are Notified to Contact BFA Law by August 19 (NASDAQ:AAPL)",
    "description": "Apple Inc. investors that lost money are notified to contact BFA Law before the August 19, 2025 securities fraud class action deadline.......",
    "url": "https://www.globenewswire.com/news-release/2025/06/24/3104203/0/en/AAPL-CLASS-ACTION-NOTICE-Apple-Inc-has-been-Sued-for-Securities-Fraud-relating-to-its-AI-Rollout-Investors-are-Notified-to-Contact-BFA-Law-by-August-19-NASDAQ-AAPL.html",
    "urlToImage": "https://ml.globenewswire.com/Resource/Download/44a256cf-d470-4d8a-af6b-dbb1b5bbb11e",
    "publishedAt": "2025-06-24T12:18:00Z",
    "content": "NEW YORK, June 24, 2025 (GLOBE NEWSWIRE) -- Leading securities law firm Bleichmar Fonti &amp; Auld LLP announces that a lawsuit has been filed against Apple Inc. (NASDAQ: AAPL) and certain of the Com\u2026 [+3685 chars]"
  },
  {
    "source": {
      "id": null,
      "name": "ETF Daily News"
    },
    "author": "MarketBeat News",
    "title": "Milestone Asset Management Group LLC Invests $4.94 Million in Apple Inc. (NASDAQ:AAPL)",
    "description": "Milestone Asset Management Group LLC acquired a new stake in Apple Inc. (NASDAQ:AAPL \u2013 Free Report) in the 4th quarter, according to its most recent Form 13F filing with the Securities & Exchange Commission. The institutional investor acquired 19,726 shares o\u2026",
    "url": "https://www.etfdailynews.com/2025/06/24/milestone-asset-management-group-llc-invests-4-94-million-in-apple-inc-nasdaqaapl/",
    "urlToImage": "https://www.americanbankingnews.com/wp-content/timthumb/timthumb.php?src=https://www.marketbeat.com/logos/apple-inc-logo-1200x675.png&w=240&h=240&zc=2",
    "publishedAt": "2025-06-24T07:16:51Z",
    "content": "Milestone Asset Management Group LLC acquired a new stake in Apple Inc. (NASDAQ:AAPL \u2013 Free Report) in the 4th quarter, according to its most recent Form 13F filing with the Securities &amp; Exchange\u2026 [+6202 chars]"
  },
  {
    "source": {
      "id": null,
      "name": "ETF Daily News"
    },
    "author": "MarketBeat News",
    "title": "Jacobs & Co. CA Sells 3,644 Shares of Apple Inc. (NASDAQ:AAPL)",
    "description": "Jacobs & Co. CA lessened its holdings in shares of Apple Inc. (NASDAQ:AAPL \u2013 Free Report) by 1.5% during the 1st quarter, HoldingsChannel.com reports. The institutional investor owned 245,305 shares of the iPhone maker\u2019s stock after selling 3,644 shares durin\u2026",
    "url": "https://www.etfdailynews.com/2025/06/24/jacobs-co-ca-sells-3644-shares-of-apple-inc-nasdaqaapl/",
    "urlToImage": "https://www.americanbankingnews.com/wp-content/timthumb/timthumb.php?src=https://www.marketbeat.com/logos/apple-inc-logo-1200x675.png&w=240&h=240&zc=2",
    "publishedAt": "2025-06-24T07:16:53Z",
    "content": "Jacobs &amp; Co. CA lessened its holdings in shares of Apple Inc. (NASDAQ:AAPL \u2013 Free Report) by 1.5% during the 1st quarter, HoldingsChannel.com reports. The institutional investor owned 245,305 sha\u2026 [+6990 chars]"
  },
  {
    "source": {
      "id": null,
      "name": "ETF Daily News"
    },
    "author": "MarketBeat News",
    "title": "Fairtree Asset Management Pty Ltd Acquires Shares of 11,154 Apple Inc. (NASDAQ:AAPL)",
    "description": "Fairtree Asset Management Pty Ltd bought a new position in shares of Apple Inc. (NASDAQ:AAPL \u2013 Free Report) during the fourth quarter, HoldingsChannel.com reports. The institutional investor bought 11,154 shares of the iPhone maker\u2019s stock, valued at approxim\u2026",
    "url": "https://www.etfdailynews.com/2025/06/24/fairtree-asset-management-pty-ltd-acquires-shares-of-11154-apple-inc-nasdaqaapl/",
    "urlToImage": "https://www.americanbankingnews.com/wp-content/timthumb/timthumb.php?src=https://www.marketbeat.com/logos/apple-inc-logo-1200x675.png&w=240&h=240&zc=2",
    "publishedAt": "2025-06-24T07:16:51Z",
    "content": "Fairtree Asset Management Pty Ltd bought a new position in shares of Apple Inc. (NASDAQ:AAPL \u2013 Free Report) during the fourth quarter, HoldingsChannel.com reports. The institutional investor bought 1\u2026 [+6092 chars]"
  },
  {
    "source": {
      "id": null,
      "name": "ETF Daily News"
    },
    "author": "MarketBeat News",
    "title": "Hobart Private Capital LLC Acquires 2,130 Shares of Apple Inc. (NASDAQ:AAPL)",
    "description": "Hobart Private Capital LLC grew its holdings in shares of Apple Inc. (NASDAQ:AAPL \u2013 Free Report) by 36.6% during the 1st quarter, Holdings Channel.com reports. The institutional investor owned 7,956 shares of the iPhone maker\u2019s stock after acquiring an additi\u2026",
    "url": "https://www.etfdailynews.com/2025/06/24/hobart-private-capital-llc-acquires-2130-shares-of-apple-inc-nasdaqaapl/",
    "urlToImage": "https://www.americanbankingnews.com/wp-content/timthumb/timthumb.php?src=https://www.marketbeat.com/logos/apple-inc-logo-1200x675.png&w=240&h=240&zc=2",
    "publishedAt": "2025-06-24T07:16:53Z",
    "content": "Hobart Private Capital LLC grew its holdings in shares of Apple Inc. (NASDAQ:AAPL \u2013 Free Report) by 36.6% during the 1st quarter, Holdings Channel.com reports. The institutional investor owned 7,956 \u2026 [+6843 chars]"
  },
  {
    "source": {
      "id": null,
      "name": "ETF Daily News"
    },
    "author": "MarketBeat News",
    "title": "Norman Fields Gottscho Capital Management LLC Reduces Stock Holdings in Apple Inc. (NASDAQ:AAPL)",
    "description": "Norman Fields Gottscho Capital Management LLC lowered its stake in shares of Apple Inc. (NASDAQ:AAPL \u2013 Free Report) by 11.0% during the first quarter, according to its most recent disclosure with the Securities and Exchange Commission. The firm owned 124,731 \u2026",
    "url": "https://www.etfdailynews.com/2025/06/24/norman-fields-gottscho-capital-management-llc-reduces-stock-holdings-in-apple-inc-nasdaqaapl/",
    "urlToImage": "https://www.americanbankingnews.com/wp-content/timthumb/timthumb.php?src=https://www.marketbeat.com/logos/apple-inc-logo-1200x675.png&w=240&h=240&zc=2",
    "publishedAt": "2025-06-24T07:16:52Z",
    "content": "Norman Fields Gottscho Capital Management LLC lowered its stake in shares of Apple Inc. (NASDAQ:AAPL \u2013 Free Report) by 11.0% during the first quarter, according to its most recent disclosure with the\u2026 [+6296 chars]"
  },
  {
    "source": {
      "id": null,
      "name": "ETF Daily News"
    },
    "author": "MarketBeat News",
    "title": "Neville Rodie & Shaw Inc. Sells 32,269 Shares of Apple Inc. (NASDAQ:AAPL)",
    "description": "Neville Rodie & Shaw Inc. cut its holdings in shares of Apple Inc. (NASDAQ:AAPL \u2013 Free Report) by 5.4% during the 1st quarter, according to its most recent disclosure with the Securities and Exchange Commission. The firm owned 568,959 shares of the iPhone mak\u2026",
    "url": "https://www.etfdailynews.com/2025/06/24/neville-rodie-shaw-inc-sells-32269-shares-of-apple-inc-nasdaqaapl/",
    "urlToImage": "https://www.americanbankingnews.com/wp-content/timthumb/timthumb.php?src=https://www.marketbeat.com/logos/apple-inc-logo-1200x675.png&w=240&h=240&zc=2",
    "publishedAt": "2025-06-24T07:16:54Z",
    "content": "Neville Rodie &amp; Shaw Inc. cut its holdings in shares of Apple Inc. (NASDAQ:AAPL \u2013 Free Report) by 5.4% during the 1st quarter, according to its most recent disclosure with the Securities and Exch\u2026 [+6410 chars]"
  },
  {
    "source": {
      "id": null,
      "name": "ETF Daily News"
    },
    "author": "MarketBeat News",
    "title": "Apple Inc. (NASDAQ:AAPL) Shares Sold by Park National Corp OH",
    "description": "Park National Corp OH reduced its stake in Apple Inc. (NASDAQ:AAPL \u2013 Free Report) by 2.8% in the 1st quarter, according to the company in its most recent 13F filing with the Securities and Exchange Commission. The institutional investor owned 488,285 shares o\u2026",
    "url": "https://www.etfdailynews.com/2025/06/24/apple-inc-nasdaqaapl-shares-sold-by-park-national-corp-oh/",
    "urlToImage": "https://www.americanbankingnews.com/wp-content/timthumb/timthumb.php?src=https://www.marketbeat.com/logos/apple-inc-logo-1200x675.png&w=240&h=240&zc=2",
    "publishedAt": "2025-06-24T07:16:51Z",
    "content": "Park National Corp OH reduced its stake in Apple Inc. (NASDAQ:AAPL \u2013 Free Report) by 2.8% in the 1st quarter, according to the company in its most recent 13F filing with the Securities and Exchange C\u2026 [+6280 chars]"
  },
  {
    "source": {
      "id": null,
      "name": "ETF Daily News"
    },
    "author": "MarketBeat News",
    "title": "Fitness Stocks To Follow Today \u2013 June 22nd",
    "description": "Apple, PDD, lululemon athletica, Toll Brothers, Paychex, Garmin, and Best Buy are the seven Fitness stocks to watch today, according to MarketBeat\u2019s stock screener tool. Fitness stocks are shares of publicly traded companies whose primary business involves he\u2026",
    "url": "https://www.etfdailynews.com/2025/06/24/fitness-stocks-to-follow-today-june-22nd/",
    "urlToImage": "https://www.americanbankingnews.com/wp-content/timthumb/timthumb.php?src=https://www.marketbeat.com/logos/apple-inc-logo-1200x675.png&w=240&h=240&zc=2",
    "publishedAt": "2025-06-24T08:10:59Z",
    "content": "Apple, PDD, lululemon athletica, Toll Brothers, Paychex, Garmin, and Best Buy are the seven Fitness stocks to watch today, according to MarketBeat\u2019s stock screener tool. Fitness stocks are shares of \u2026 [+7942 chars]"
  },
  {
    "source": {
      "id": null,
      "name": "ETF Daily News"
    },
    "author": "MarketBeat News",
    "title": "Avant Financial Advisors LLC Makes New $4.50 Million Investment in Apple Inc. (NASDAQ:AAPL)",
    "description": "Avant Financial Advisors LLC acquired a new position in Apple Inc. (NASDAQ:AAPL \u2013 Free Report) in the fourth quarter, according to its most recent filing with the Securities and Exchange Commission (SEC). The firm acquired 17,967 shares of the iPhone maker\u2019s \u2026",
    "url": "https://www.etfdailynews.com/2025/06/24/avant-financial-advisors-llc-makes-new-4-50-million-investment-in-apple-inc-nasdaqaapl/",
    "urlToImage": "https://www.americanbankingnews.com/wp-content/timthumb/timthumb.php?src=https://www.marketbeat.com/logos/apple-inc-logo-1200x675.png&w=240&h=240&zc=2",
    "publishedAt": "2025-06-24T07:16:49Z",
    "content": "Avant Financial Advisors LLC acquired a new position in Apple Inc. (NASDAQ:AAPL \u2013 Free Report) in the fourth quarter, according to its most recent filing with the Securities and Exchange Commission (\u2026 [+6126 chars]"
  },
  {
    "source": {
      "id": null,
      "name": "ETF Daily News"
    },
    "author": "MarketBeat News",
    "title": "Promising Large Cap Stocks To Add to Your Watchlist \u2013 June 22nd",
    "description": "Tesla, NVIDIA, Invesco QQQ, Circle Internet Group, and Apple are the five Large Cap stocks to watch today, according to MarketBeat\u2019s stock screener tool. Large-cap stocks are shares of companies whose total market value typically exceeds $10 billion. These se\u2026",
    "url": "https://www.etfdailynews.com/2025/06/24/promising-large-cap-stocks-to-add-to-your-watchlist-june-22nd/",
    "urlToImage": "https://www.americanbankingnews.com/wp-content/timthumb/timthumb.php?src=https://www.marketbeat.com/logos/tesla-inc-logo-1200x675.png?v=20221020135629&w=240&h=240&zc=2",
    "publishedAt": "2025-06-24T17:16:44Z",
    "content": "Tesla, NVIDIA, Invesco QQQ, Circle Internet Group, and Apple are the five Large Cap stocks to watch today, according to MarketBeat\u2019s stock screener tool. Large-cap stocks are shares of companies whos\u2026 [+5655 chars]"
  },
  {
    "source": {
      "id": null,
      "name": "ETF Daily News"
    },
    "author": "MarketBeat News",
    "title": "Apple Inc. (NASDAQ:AAPL) Shares Sold by Cacti Asset Management LLC",
    "description": "Cacti Asset Management LLC lessened its position in Apple Inc. (NASDAQ:AAPL \u2013 Free Report) by 0.2% during the 1st quarter, according to the company in its most recent disclosure with the Securities and Exchange Commission (SEC). The institutional investor own\u2026",
    "url": "https://www.etfdailynews.com/2025/06/24/apple-inc-nasdaqaapl-shares-sold-by-cacti-asset-management-llc/",
    "urlToImage": "https://www.americanbankingnews.com/wp-content/timthumb/timthumb.php?src=https://www.marketbeat.com/logos/apple-inc-logo-1200x675.png&w=240&h=240&zc=2",
    "publishedAt": "2025-06-24T07:16:55Z",
    "content": "Cacti Asset Management LLC lessened its position in Apple Inc. (NASDAQ:AAPL \u2013 Free Report) by 0.2% during the 1st quarter, according to the company in its most recent disclosure with the Securities a\u2026 [+6956 chars]"
  },
  {
    "source": {
      "id": null,
      "name": "ETF Daily News"
    },
    "author": "MarketBeat News",
    "title": "Rempart Asset Management Inc. Decreases Stock Holdings in Apple Inc. (NASDAQ:AAPL)",
    "description": "Rempart Asset Management Inc. lessened its holdings in Apple Inc. (NASDAQ:AAPL \u2013 Free Report) by 6.6% during the 1st quarter, according to its most recent disclosure with the Securities and Exchange Commission (SEC). The institutional investor owned 7,377 sha\u2026",
    "url": "https://www.etfdailynews.com/2025/06/24/rempart-asset-management-inc-decreases-stock-holdings-in-apple-inc-nasdaqaapl/",
    "urlToImage": "https://www.americanbankingnews.com/wp-content/timthumb/timthumb.php?src=https://www.marketbeat.com/logos/apple-inc-logo-1200x675.png&w=240&h=240&zc=2",
    "publishedAt": "2025-06-24T07:16:50Z",
    "content": "Rempart Asset Management Inc. lessened its holdings in Apple Inc. (NASDAQ:AAPL \u2013 Free Report) by 6.6% during the 1st quarter, according to its most recent disclosure with the Securities and Exchange \u2026 [+6217 chars]"
  },
  {
    "source": {
      "id": null,
      "name": "ETF Daily News"
    },
    "author": "MarketBeat News",
    "title": "Apple Inc. (NASDAQ:AAPL) Shares Sold by Modus Advisors LLC",
    "description": "Modus Advisors LLC lowered its stake in shares of Apple Inc. (NASDAQ:AAPL \u2013 Free Report) by 0.4% during the first quarter, Holdings Channel reports. The fund owned 47,813 shares of the iPhone maker\u2019s stock after selling 212 shares during the period. Apple com\u2026",
    "url": "https://www.etfdailynews.com/2025/06/24/apple-inc-nasdaqaapl-shares-sold-by-modus-advisors-llc/",
    "urlToImage": "https://www.americanbankingnews.com/wp-content/timthumb/timthumb.php?src=https://www.marketbeat.com/logos/apple-inc-logo-1200x675.png&w=240&h=240&zc=2",
    "publishedAt": "2025-06-24T07:16:50Z",
    "content": "Modus Advisors LLC lowered its stake in shares of Apple Inc. (NASDAQ:AAPL \u2013 Free Report) by 0.4% during the first quarter, Holdings Channel reports. The fund owned 47,813 shares of the iPhone maker\u2019s\u2026 [+6927 chars]"
  },
  {
    "source": {
      "id": null,
      "name": "ETF Daily News"
    },
    "author": "MarketBeat News",
    "title": "Retail Stocks To Follow Now \u2013 June 22nd",
    "description": "Tesla, Apple, Microsoft, Amazon.com, and UnitedHealth Group are the five Retail stocks to watch today, according to MarketBeat\u2019s stock screener tool. Retail stocks are shares of publicly traded companies whose core business involves selling consumer goods and\u2026",
    "url": "https://www.etfdailynews.com/2025/06/24/retail-stocks-to-follow-now-june-22nd/",
    "urlToImage": "https://www.americanbankingnews.com/wp-content/timthumb/timthumb.php?src=https://www.marketbeat.com/logos/tesla-inc-logo-1200x675.png?v=20221020135629&w=240&h=240&zc=2",
    "publishedAt": "2025-06-24T06:40:45Z",
    "content": "Tesla, Apple, Microsoft, Amazon.com, and UnitedHealth Group are the five Retail stocks to watch today, according to MarketBeat\u2019s stock screener tool. Retail stocks are shares of publicly traded compa\u2026 [+6373 chars]"
  },
  {
    "source": {
      "id": null,
      "name": "Pypi.org"
    },
    "author": "jakub@quantjourney.pro",
    "title": "quantjourney-bidask added to PyPI",
    "description": "Efficient bid-ask spread estimator from OHLC prices",
    "url": "https://pypi.org/project/quantjourney-bidask/",
    "urlToImage": "https://pypi.org/static/images/twitter.abaf4b19.webp",
    "publishedAt": "2025-06-24T19:57:03Z",
    "content": "The quantjourney-bidask library provides an efficient estimator for calculating bid-ask spreads from open, high, low, and close (OHLC) prices, based on the methodology described in:\r\nArdia, D., Guido\u2026 [+3670 chars]"
  }
]